deepBreaks/__init__.py
deepBreaks/deepBreaks.py
deepBreaks/models.py
deepBreaks/preprocessing.py
deepBreaks/utils.py
deepBreaks/visualization.py
deepBreaks-1.1.0.data/data/requirements.txt
deepBreaks-1.1.0.dist-info/LICENSE.txt
deepBreaks-1.1.0.dist-info/METADATA
deepBreaks-1.1.0.dist-info/WHEEL
deepBreaks-1.1.0.dist-info/entry_points.txt
deepBreaks-1.1.0.dist-info/top_level.txt
deepBreaks-1.1.0.dist-info/RECORD
