Metadata-Version: 2.1
Name: deepBreaks
Version: 1.1.0
Summary: deepBreaks: a machine learning tool for identifying and prioritizing genotype-phenotype associations
Home-page: http://github.com/omicsEye/deepBreaks
Author: Mahdi Baghbanzadeh
Author-email: mbagh@gwu.edu
License: MIT
Keywords: machine learning,genomics,sequencing data
Platform: Linux
Platform: MacOS
Platform: Windows
Classifier: Programming Language :: Python
Classifier: Development Status :: 5 - Production/Stable
Classifier: Environment :: Console
Classifier: Operating System :: MacOS
Classifier: Operating System :: Unix
Classifier: Operating System :: Microsoft :: Windows
Classifier: Programming Language :: Python :: 3.8
Classifier: Programming Language :: Python :: 3.9
Classifier: Topic :: Scientific/Engineering :: Bio-Informatics
License-File: LICENSE.txt
Requires-Dist: setuptools (>=67.7.2)
Requires-Dist: pandas (>=1.4.3)
Requires-Dist: numpy (>=1.19.5)
Requires-Dist: scikit-learn (>=1.2.2)
Requires-Dist: scipy (>=1.10.1)
Requires-Dist: seaborn (>=0.11.2)
Requires-Dist: matplotlib (>=3.5.2)
Requires-Dist: joblib (>=1.1.0)
Requires-Dist: xgboost (>=1.7.5)
Requires-Dist: lightgbm (>=3.3.5)
